SlaterPythonGames/2048Icon.png
SlaterPythonGames/AdvancedAI.py
SlaterPythonGames/CoinGame.py
SlaterPythonGames/ConnectFour.py
SlaterPythonGames/CountryGuessingGame.py
SlaterPythonGames/Hangman.py
SlaterPythonGames/TicTacToe1Player.py
SlaterPythonGames/TicTacToe2Player.py
SlaterPythonGames/TwentyFortyEight.py
SlaterPythonGames/Warships.py
SlaterPythonGames/Warships2.py
SlaterPythonGames/Warships2Account.py
SlaterPythonGames/WarshipsIcon.png
SlaterPythonGames/__AIFleets__.py
SlaterPythonGames/__AIShots__.py
SlaterPythonGames/__init__.py
SlaterPythonGames/icons/battleshipOutline.png
SlaterPythonGames/icons/battleshipOutlineOriginal.png
SlaterPythonGames/icons/carrierOutline.png
SlaterPythonGames/icons/carrierOutlineOriginal.png
SlaterPythonGames/icons/cruiserOutline.png
SlaterPythonGames/icons/cruiserOutlineOriginal.png
SlaterPythonGames/icons/destroyerOutline.png
SlaterPythonGames/icons/destroyerOutlineOriginal.png
SlaterPythonGames/icons/reticle.png
SlaterPythonGames/icons/settingsIconActive.png
SlaterPythonGames/icons/settingsIconInactive.png
SlaterPythonGames/icons/submarineOutline.png
SlaterPythonGames/icons/submarineOutlineOriginal.png
SlaterPythonGames-1.7.dist-info/LICENSE
SlaterPythonGames-1.7.dist-info/METADATA
SlaterPythonGames-1.7.dist-info/WHEEL
SlaterPythonGames-1.7.dist-info/top_level.txt
SlaterPythonGames-1.7.dist-info/RECORD
