Metadata-Version: 2.1
Name: SlaterPythonGames
Version: 1.7
Summary: An updated version of rygames, a collection of games written in Python
Home-page: https://github.com/rjslater2000/SlaterPythonGames
Author: Ryan J. Slater
Author-email: ryan.j.slater.2@gmail.com
License: UNKNOWN
Keywords: games,battleship,python
Platform: UNKNOWN
Classifier: Programming Language :: Python :: 3
Classifier: License :: OSI Approved :: MIT License
Classifier: Operating System :: OS Independent
Requires-Dist: pygame
Requires-Dist: numpy
Requires-Dist: matplotlib
Requires-Dist: names
Requires-Dist: requests
